weedcv/__init__.py
weedcv/weedcv/__init__.py
weedcv/weedcv/_debug.py
weedcv/weedcv/apply_mask.py
weedcv/weedcv/classes.py
weedcv/weedcv/clear_edges.py
weedcv/weedcv/color_palette.py
weedcv/weedcv/combine_component.py
weedcv/weedcv/create_foreground.py
weedcv/weedcv/crop_contours.py
weedcv/weedcv/csv_reporter.py
weedcv/weedcv/filter_components.py
weedcv/weedcv/load_img.py
weedcv/weedcv/make_exg.py
weedcv/weedcv/morph_close.py
weedcv/weedcv/otsu_thresh.py
weedcv/weedcv/reporter.py
weedcv/weedcv/save_image.py
weedcv/weedcv/show_image.py
weedcv/weedcv/watershed.py
weedcv/weedcv/tests/__init__.py
weedcv/weedcv/tests/tests.py
weedcv-1.0.5.dist-info/LICENSE
weedcv-1.0.5.dist-info/METADATA
weedcv-1.0.5.dist-info/WHEEL
weedcv-1.0.5.dist-info/top_level.txt
weedcv-1.0.5.dist-info/RECORD
